Workbook

Sheet Dashboard
A1: E-COMMERCE SALES DASHBOARD
I2: Portfolio Project • Synthetic FY2025 Dataset
A3: FY2025 performance overview • Revenue, orders, customers, products, regions & monthly trends
A5: Total Revenue | D5: Total Orders | G5: Unique Customers | J5: Avg Order Value | M5: Units Sold
A6: =SUM(Data!J2:J1201) -> 132900.67 | D6: =COUNTA(Data!A2:A1201) -> 1200 | G6: =SUM(Lists!G1:G600) -> 521 | J6: =SUM(Data!J2:J1201)/COUNTA(Data!A2:A1201) -> 110.75056 | M6: =SUM(Data!G2:G1201) -> 2005
A10: Month | B10: Revenue | C10: Orders | D10: AOV | F10: Category | G10: Revenue | I10: Region | J10: Revenue | L10: Product Mix | M10: Revenue | N10: Units
A11: Jan | B11: =SUMIFS(Data!$J$2:$J$1201,Data!$B$2:$B$1201,">="&DATE(2025,ROW()-10,1),Data!$B$2:$B$1201,"<"&EDATE(DATE(2025,ROW()-10,1),1)) -> 10780.72 | C11: =COUNTIFS(Data!$B$2:$B$1201,">="&DATE(2025,ROW()-10,1),Data!$B$2:$B$1201,"<"&EDATE(DATE(2025,ROW()-10,1),1)) -> 90 | D11: =B11/C11 -> 119.78578 | F11: Electronics | G11: =SUMIF(Data!$E$2:$E$1201,F11,Data!$J$2:$J$1201) -> 39748.61 | I11: North | J11: =SUMIF(Data!$D$2:$D$1201,I11,Data!$J$2:$J$1201) -> 30639.1 | L11: Wireless Headphones | M11: =SUMIF(Data!$F$2:$F$1201,L11,Data!$J$2:$J$1201) -> 11289.56 | N11: =SUMIF(Data!$F$2:$F$1201,L11,Data!$G$2:$G$1201) -> 151
A12: Feb | B12: =SUMIFS(Data!$J$2:$J$1201,Data!$B$2:$B$1201,">="&DATE(2025,ROW()-10,1),Data!$B$2:$B$1201,"<"&EDATE(DATE(2025,ROW()-10,1),1)) -> 13360.77 | C12: =COUNTIFS(Data!$B$2:$B$1201,">="&DATE(2025,ROW()-10,1),Data!$B$2:$B$1201,"<"&EDATE(DATE(2025,ROW()-10,1),1)) -> 104 | D12: =B12/C12 -> 128.46894 | F12: Fashion | G12: =SUMIF(Data!$E$2:$E$1201,F12,Data!$J$2:$J$1201) -> 20053.88 | I12: South | J12: =SUMIF(Data!$D$2:$D$1201,I12,Data!$J$2:$J$1201) -> 32657.35 | L12: Smart Watch | M12: =SUMIF(Data!$F$2:$F$1201,L12,Data!$J$2:$J$1201) -> 19601.96 | N12: =SUMIF(Data!$F$2:$F$1201,L12,Data!$G$2:$G$1201) -> 160
A13: Mar | B13: =SUMIFS(Data!$J$2:$J$1201,Data!$B$2:$B$1201,">="&DATE(2025,ROW()-10,1),Data!$B$2:$B$1201,"<"&EDATE(DATE(2025,ROW()-10,1),1)) -> 10887.22 | C13: =COUNTIFS(Data!$B$2:$B$1201,">="&DATE(2025,ROW()-10,1),Data!$B$2:$B$1201,"<"&EDATE(DATE(2025,ROW()-10,1),1)) -> 99 | D13: =B13/C13 -> 109.97192 | F13: Home & Kitchen | G13: =SUMIF(Data!$E$2:$E$1201,F13,Data!$J$2:$J$1201) -> 40945.34 | I13: East | J13: =SUMIF(Data!$D$2:$D$1201,I13,Data!$J$2:$J$1201) -> 34360.92 | L13: Bluetooth Speaker | M13: =SUMIF(Data!$F$2:$F$1201,L13,Data!$J$2:$J$1201) -> 8857.09 | N13: =SUMIF(Data!$F$2:$F$1201,L13,Data!$G$2:$G$1201) -> 158
A14: Apr | B14: =SUMIFS(Data!$J$2:$J$1201,Data!$B$2:$B$1201,">="&DATE(2025,ROW()-10,1),Data!$B$2:$B$1201,"<"&EDATE(DATE(2025,ROW()-10,1),1)) -> 8211.36 | C14: =COUNTIFS(Data!$B$2:$B$1201,">="&DATE(2025,ROW()-10,1),Data!$B$2:$B$1201,"<"&EDATE(DATE(2025,ROW()-10,1),1)) -> 80 | D14: =B14/C14 -> 102.642 | F14: Beauty | G14: =SUMIF(Data!$E$2:$E$1201,F14,Data!$J$2:$J$1201) -> 16698.49 | I14: West | J14: =SUMIF(Data!$D$2:$D$1201,I14,Data!$J$2:$J$1201) -> 35243.3 | L14: Running Shoes | M14: =SUMIF(Data!$F$2:$F$1201,L14,Data!$J$2:$J$1201) -> 11038.23 | N14: =SUMIF(Data!$F$2:$F$1201,L14,Data!$G$2:$G$1201) -> 157
A15: May | B15: =SUMIFS(Data!$J$2:$J$1201,Data!$B$2:$B$1201,">="&DATE(2025,ROW()-10,1),Data!$B$2:$B$1201,"<"&EDATE(DATE(2025,ROW()-10,1),1)) -> 9466.19 | C15: =COUNTIFS(Data!$B$2:$B$1201,">="&DATE(2025,ROW()-10,1),Data!$B$2:$B$1201,"<"&EDATE(DATE(2025,ROW()-10,1),1)) -> 92 | D15: =B15/C15 -> 102.89337 | F15: Sports | G15: =SUMIF(Data!$E$2:$E$1201,F15,Data!$J$2:$J$1201) -> 15454.35 | L15: Yoga Mat | M15: =SUMIF(Data!$F$2:$F$1201,L15,Data!$J$2:$J$1201) -> 4416.12 | N15: =SUMIF(Data!$F$2:$F$1201,L15,Data!$G$2:$G$1201) -> 162
A16: Jun | B16: =SUMIFS(Data!$J$2:$J$1201,Data!$B$2:$B$1201,">="&DATE(2025,ROW()-10,1),Data!$B$2:$B$1201,"<"&EDATE(DATE(2025,ROW()-10,1),1)) -> 12092.84 | C16: =COUNTIFS(Data!$B$2:$B$1201,">="&DATE(2025,ROW()-10,1),Data!$B$2:$B$1201,"<"&EDATE(DATE(2025,ROW()-10,1),1)) -> 108 | D16: =B16/C16 -> 111.97074 | L16: Coffee Maker | M16: =SUMIF(Data!$F$2:$F$1201,L16,Data!$J$2:$J$1201) -> 15785.3 | N16: =SUMIF(Data!$F$2:$F$1201,L16,Data!$G$2:$G$1201) -> 184
A17: Jul | B17: =SUMIFS(Data!$J$2:$J$1201,Data!$B$2:$B$1201,">="&DATE(2025,ROW()-10,1),Data!$B$2:$B$1201,"<"&EDATE(DATE(2025,ROW()-10,1),1)) -> 12095.22 | C17: =COUNTIFS(Data!$B$2:$B$1201,">="&DATE(2025,ROW()-10,1),Data!$B$2:$B$1201,"<"&EDATE(DATE(2025,ROW()-10,1),1)) -> 103 | D17: =B17/C17 -> 117.42932 | L17: Air Fryer | M17: =SUMIF(Data!$F$2:$F$1201,L17,Data!$J$2:$J$1201) -> 19717.72 | N17: =SUMIF(Data!$F$2:$F$1201,L17,Data!$G$2:$G$1201) -> 175
A18: Aug | B18: =SUMIFS(Data!$J$2:$J$1201,Data!$B$2:$B$1201,">="&DATE(2025,ROW()-10,1),Data!$B$2:$B$1201,"<"&EDATE(DATE(2025,ROW()-10,1),1)) -> 10490.2 | C18: =COUNTIFS(Data!$B$2:$B$1201,">="&DATE(2025,ROW()-10,1),Data!$B$2:$B$1201,"<"&EDATE(DATE(2025,ROW()-10,1),1)) -> 99 | D18: =B18/C18 -> 105.96162 | L18: Backpack | M18: =SUMIF(Data!$F$2:$F$1201,L18,Data!$J$2:$J$1201) -> 8940.11 | N18: =SUMIF(Data!$F$2:$F$1201,L18,Data!$G$2:$G$1201) -> 192
A19: Sep | B19: =SUMIFS(Data!$J$2:$J$1201,Data!$B$2:$B$1201,">="&DATE(2025,ROW()-10,1),Data!$B$2:$B$1201,"<"&EDATE(DATE(2025,ROW()-10,1),1)) -> 9308.16 | C19: =COUNTIFS(Data!$B$2:$B$1201,">="&DATE(2025,ROW()-10,1),Data!$B$2:$B$1201,"<"&EDATE(DATE(2025,ROW()-10,1),1)) -> 90 | D19: =B19/C19 -> 103.424
A20: Oct | B20: =SUMIFS(Data!$J$2:$J$1201,Data!$B$2:$B$1201,">="&DATE(2025,ROW()-10,1),Data!$B$2:$B$1201,"<"&EDATE(DATE(2025,ROW()-10,1),1)) -> 10844.66 | C20: =COUNTIFS(Data!$B$2:$B$1201,">="&DATE(2025,ROW()-10,1),Data!$B$2:$B$1201,"<"&EDATE(DATE(2025,ROW()-10,1),1)) -> 108 | D20: =B20/C20 -> 100.41352
A21: Nov | B21: =SUMIFS(Data!$J$2:$J$1201,Data!$B$2:$B$1201,">="&DATE(2025,ROW()-10,1),Data!$B$2:$B$1201,"<"&EDATE(DATE(2025,ROW()-10,1),1)) -> 11179.94 | C21: =COUNTIFS(Data!$B$2:$B$1201,">="&DATE(2025,ROW()-10,1),Data!$B$2:$B$1201,"<"&EDATE(DATE(2025,ROW()-10,1),1)) -> 107 | D21: =B21/C21 -> 104.48542
A22: Dec | B22: =SUMIFS(Data!$J$2:$J$1201,Data!$B$2:$B$1201,">="&DATE(2025,ROW()-10,1),Data!$B$2:$B$1201,"<"&EDATE(DATE(2025,ROW()-10,1),1)) -> 14183.39 | C22: =COUNTIFS(Data!$B$2:$B$1201,">="&DATE(2025,ROW()-10,1),Data!$B$2:$B$1201,"<"&EDATE(DATE(2025,ROW()-10,1),1)) -> 120 | D22: =B22/C22 -> 118.19492
A24: EXECUTIVE INSIGHTS
A25: ="Revenue is "&TEXT(B22/B11-1,"0%")&" different from January. "&TEXT(MAX(G11:G15)/SUM(G11:G15),"0%")&" of category revenue comes from the leading category. "&TEXT(MAX(J11:J14)/SUM(J11:J14),"0%")&" of regional revenue comes from the top region." -> Revenue is 32% different from January. 31% of category revenue comes from the leading category. 27% of regional revenue comes from the top region.

Sheet Data
A1: Order ID | B1: Order Date | C1: Customer ID | D1: Region | E1: Category | F1: Product | G1: Quantity | H1: Unit Price | I1: Discount | J1: Revenue | K1: Channel
A2: ORD-00001 | B2: 45985 | C2: CUST-0143 | D2: North | E2: Electronics | F2: Smart Watch | G2: 1 | H2: 121.36 | I2: 0 | J2: 121.36 | K2: Marketplace
A3: ORD-00002 | B3: 45937 | C3: CUST-0224 | D3: South | E3: Electronics | F3: Smart Watch | G3: 2 | H3: 111 | I3: 0 | J3: 222 | K3: Marketplace
A4: ORD-00003 | B4: 45966 | C4: CUST-0430 | D4: South | E4: Electronics | F4: Wireless Headphones | G4: 2 | H4: 85.82 | I4: 0.15 | J4: 145.89 | K4: Mobile App
A5: ORD-00004 | B5: 45959 | C5: CUST-0433 | D5: East | E5: Sports | F5: Yoga Mat | G5: 2 | H5: 24.71 | I5: 0 | J5: 49.42 | K5: Mobile App
A6: ORD-00005 | B6: 45737 | C6: CUST-0390 | D6: North | E6: Sports | F6: Running Shoes | G6: 4 | H6: 71.12 | I6: 0 | J6: 284.48 | K6: Mobile App
A7: ORD-00006 | B7: 45834 | C7: CUST-0550 | D7: North | E7: Beauty | F7: Skincare Set | G7: 1 | H7: 38.9 | I7: 0.1 | J7: 35.01 | K7: Mobile App
A8: ORD-00007 | B8: 45698 | C8: CUST-0592 | D8: South | E8: Fashion | F8: Sneakers | G8: 1 | H8: 72.96 | I8: 0.05 | J8: 69.31 | K8: Marketplace
A9: ORD-00008 | B9: 45693 | C9: CUST-0239 | D9: North | E9: Electronics | F9: Wireless Headphones | G9: 2 | H9: 87.3 | I9: 0 | J9: 174.6 | K9: Mobile App
A10: ORD-00009 | B10: 45800 | C10: CUST-0364 | D10: South | E10: Fashion | F10: Backpack | G10: 2 | H10: 47.55 | I10: 0.05 | J10: 90.34 | K10: Marketplace
A11: ORD-00010 | B11: 45794 | C11: CUST-0176 | D11: South | E11: Home & Kitchen | F11: Desk Lamp | G11: 3 | H11: 41.49 | I11: 0.15 | J11: 105.8 | K11: Website
A12: ORD-00011 | B12: 45894 | C12: CUST-0225 | D12: East | E12: Home & Kitchen | F12: Air Fryer | G12: 1 | H12: 137.49 | I12: 0.15 | J12: 116.87 | K12: Website
A13: ORD-00012 | B13: 45775 | C13: CUST-0217 | D13: East | E13: Electronics | F13: Wireless Headphones | G13: 2 | H13: 77.61 | I13: 0 | J13: 155.22 | K13: Website
... A1201: ORD-01200 | B1201: 45801 | C1201: CUST-0487 | D1201: West | E1201: Home & Kitchen | F1201: Desk Lamp | G1201: 2 | H1201: 36.35 | I1201: 0.1 | J1201: 65.43 | K1201: Marketplace

Sheet Lists
A1: 45658 | B1: North | C1: Electronics | D1: Wireless Headphones | E1: Website | F1: CUST-0001 | G1: =IF(COUNTIF(Data!$C$2:$C$1201,F1)>0,1,0) -> 1
A2: 45689 | B2: South | C2: Fashion | D2: Smart Watch | E2: Mobile App | F2: CUST-0002 | G2: =IF(COUNTIF(Data!$C$2:$C$1201,F2)>0,1,0) -> 1
A3: 45717 | B3: East | C3: Home & Kitchen | D3: Bluetooth Speaker | E3: Marketplace | F3: CUST-0003 | G3: =IF(COUNTIF(Data!$C$2:$C$1201,F3)>0,1,0) -> 1
A4: 45748 | B4: West | C4: Beauty | D4: Running Shoes | F4: CUST-0004 | G4: =IF(COUNTIF(Data!$C$2:$C$1201,F4)>0,1,0) -> 1
A5: 45778 | C5: Sports | D5: Yoga Mat | F5: CUST-0005 | G5: =IF(COUNTIF(Data!$C$2:$C$1201,F5)>0,1,0) -> 1
A6: 45809 | D6: Coffee Maker | F6: CUST-0006 | G6: =IF(COUNTIF(Data!$C$2:$C$1201,F6)>0,1,0) -> 1
A7: 45839 | D7: Air Fryer | F7: CUST-0007 | G7: =IF(COUNTIF(Data!$C$2:$C$1201,F7)>0,1,0) -> 1
A8: 45870 | D8: Backpack | F8: CUST-0008 | G8: =IF(COUNTIF(Data!$C$2:$C$1201,F8)>0,1,0) -> 1
A9: 45901 | D9: Sneakers | F9: CUST-0009 | G9: =IF(COUNTIF(Data!$C$2:$C$1201,F9)>0,1,0) -> 0
A10: 45931 | D10: Skincare Set | F10: CUST-0010 | G10: =IF(COUNTIF(Data!$C$2:$C$1201,F10)>0,1,0) -> 1
A11: 45962 | D11: Hair Dryer | F11: CUST-0011 | G11: =IF(COUNTIF(Data!$C$2:$C$1201,F11)>0,1,0) -> 1
A12: 45992 | D12: Desk Lamp | F12: CUST-0012 | G12: =IF(COUNTIF(Data!$C$2:$C$1201,F12)>0,1,0) -> 1
F13: CUST-0013 | G13: =IF(COUNTIF(Data!$C$2:$C$1201,F13)>0,1,0) -> 1
F14: CUST-0014 | G14: =IF(COUNTIF(Data!$C$2:$C$1201,F14)>0,1,0) -> 0
F15: CUST-0015 | G15: =IF(COUNTIF(Data!$C$2:$C$1201,F15)>0,1,0) -> 0
F16: CUST-0016 | G16: =IF(COUNTIF(Data!$C$2:$C$1201,F16)>0,1,0) -> 1
F17: CUST-0017 | G17: =IF(COUNTIF(Data!$C$2:$C$1201,F17)>0,1,0) -> 1
F18: CUST-0018 | G18: =IF(COUNTIF(Data!$C$2:$C$1201,F18)>0,1,0) -> 0
F19: CUST-0019 | G19: =IF(COUNTIF(Data!$C$2:$C$1201,F19)>0,1,0) -> 1
F20: CUST-0020 | G20: =IF(COUNTIF(Data!$C$2:$C$1201,F20)>0,1,0) -> 1
F21: CUST-0021 | G21: =IF(COUNTIF(Data!$C$2:$C$1201,F21)>0,1,0) -> 1
F22: CUST-0022 | G22: =IF(COUNTIF(Data!$C$2:$C$1201,F22)>0,1,0) -> 1
F23: CUST-0023 | G23: =IF(COUNTIF(Data!$C$2:$C$1201,F23)>0,1,0) -> 1
F24: CUST-0024 | G24: =IF(COUNTIF(Data!$C$2:$C$1201,F24)>0,1,0) -> 1
... F600: CUST-0600 | G600: =IF(COUNTIF(Data!$C$2:$C$1201,F600)>0,1,0) -> 1
